hiduu/_init_.py
hiduu/hiduu.py
HIDUU-1.0.7.dist-info/LICENSE
HIDUU-1.0.7.dist-info/METADATA
HIDUU-1.0.7.dist-info/WHEEL
HIDUU-1.0.7.dist-info/top_level.txt
HIDUU-1.0.7.dist-info/RECORD
