Metadata-Version: 2.1
Name: HIDUU
Version: 1.0.7
Summary: A package to upload information to Cerner HealtheIntent
Home-page: https://github.com/patrickgagnon/HIDUU
Author: Patrick Gagnon
Author-email: plgagnon00@gmail.com
License: UNKNOWN
Platform: UNKNOWN
